<annotation>
	<folder>onion_rings</folder>
	<filename>74527.jpg</filename>
	<path>C:\Users\arunr\Downloads\windows_v1.8.0\Dataset\onion_rings\74527.jpg</path>
	<source>
		<database>Unknown</database>
	</source>
	<size>
		<width>512</width>
		<height>383</height>
		<depth>3</depth>
	</size>
	<segmented>0</segmented>
	<object>
		<name>onion_rings 156 calories</name>
		<pose>Unspecified</pose>
		<truncated>0</truncated>
		<difficult>0</difficult>
		<bndbox>
			<xmin>208</xmin>
			<ymin>10</ymin>
			<xmax>447</xmax>
			<ymax>284</ymax>
		</bndbox>
	</object>
</annotation>
